README.rst
setup.cfg
setup.py
fabia/__init__.py
fabia/_fabia.c
fabia/fabia.py
fabia/generate_dataset.py
fabia.egg-info/PKG-INFO
fabia.egg-info/SOURCES.txt
fabia.egg-info/dependency_links.txt
fabia.egg-info/pbr.json
fabia.egg-info/requires.txt
fabia.egg-info/top_level.txt