Metadata-Version: 1.1
Name: fabia
Version: 2016.8
Summary: Fabia Biclustering Algorithm
Home-page: https://github.com/bioinf-jku/pyfabia
Author: Thomas Unterthiner
Author-email: unterthiner@bioinf.jku.at
License: GPL v2
Keywords: Machine Learning Biclustering Fabia
Platform: UNKNOWN
Classifier: Intended Audience :: Science/Research
Classifier: Topic :: Scientific/Engineering
Classifier: Topic :: Software Development
Classifier: License :: OSI Approved :: BSD License
Classifier: Programming Language :: Python :: 2
Classifier: Programming Language :: Python :: 2.6
Classifier: Programming Language :: Python :: 2.7
Classifier: Programming Language :: Python :: 3
Classifier: Programming Language :: Python :: 3.3
Classifier: Programming Language :: Python :: 3.4
Classifier: Programming Language :: Python :: 3.5
Classifier: Programming Language :: Python :: 3.6
